{"time":{"updated":"Aug 20, 2024 01:55:45 UTC","updatedISO":"2024-08-20T01:55:45+00:00","updateduk":"Aug 20, 2024 at 02:55 BST"},"disclaimer":"This data was produced from the CoinDesk Bitcoin Price Index (USD). Non-USD currency data converted using hourly conversion rate from openexchangerates.org","chartName":"Bitcoin","bpi":{"USD":{"code":"USD","symbol":"&#36;","rate":"60,476.162","description":"United States Dollar","rate_float":60476.1624},"GBP":{"code":"GBP","symbol":"&pound;","rate":"46,570.092","description":"British Pound Sterling","rate_float":46570.0922},"EUR":{"code":"EUR","symbol":"&euro;","rate":"54,571.33","description":"Euro","rate_float":54571.3304},"CNY":{"code":"CNY","symbol":"&yen;","rate":"431,582.086","description":"Chinese Yuan","rate_float":431582.0855}}}