{"time":{"updated":"Oct 22, 2024 19:27:40 UTC","updatedISO":"2024-10-22T19:27:40+00:00","updateduk":"Oct 22, 2024 at 20:27 BST"},"disclaimer":"This data was produced from the CoinDesk Bitcoin Price Index (USD). Non-USD currency data converted using hourly conversion rate from openexchangerates.org","chartName":"Bitcoin","bpi":{"USD":{"code":"USD","symbol":"&#36;","rate":"67,485.198","description":"United States Dollar","rate_float":67485.1976},"GBP":{"code":"GBP","symbol":"&pound;","rate":"51,997.48","description":"British Pound Sterling","rate_float":51997.4798},"EUR":{"code":"EUR","symbol":"&euro;","rate":"62,487.514","description":"Euro","rate_float":62487.5139},"CNY":{"code":"CNY","symbol":"&yen;","rate":"480,703.811","description":"Chinese Yuan","rate_float":480703.8114}}}