{"time":{"updated":"Nov 1, 2021 07:21:00 UTC","updatedISO":"2021-11-01T07:21:00+00:00","updateduk":"Nov 1, 2021 at 07:21 GMT"},"disclaimer":"This data was produced from the CoinDesk Bitcoin Price Index (USD). Non-USD currency data converted using hourly conversion rate from openexchangerates.org","chartName":"Bitcoin","bpi":{"USD":{"code":"USD","symbol":"&#36;","rate":"62,022.7383","description":"United States Dollar","rate_float":62022.7383},"GBP":{"code":"GBP","symbol":"&pound;","rate":"45,384.7666","description":"British Pound Sterling","rate_float":45384.7666},"EUR":{"code":"EUR","symbol":"&euro;","rate":"53,675.4701","description":"Euro","rate_float":53675.4701},"CNY":{"code":"CNY","symbol":"&yen;","rate":"40,202.5000","description":"Chinese Yuan","rate_float":40202.5}}}