{"time":{"updated":"Jan 11, 2024 04:35:39 UTC","updatedISO":"2024-01-11T04:35:39+00:00","updateduk":"Jan 11, 2024 at 04:35 GMT"},"disclaimer":"This data was produced from the CoinDesk Bitcoin Price Index (USD). Non-USD currency data converted using hourly conversion rate from openexchangerates.org","chartName":"Bitcoin","bpi":{"USD":{"code":"USD","symbol":"&#36;","rate":"46,485.681","description":"United States Dollar","rate_float":46485.6809},"GBP":{"code":"GBP","symbol":"&pound;","rate":"36,411.397","description":"British Pound Sterling","rate_float":36411.3971},"EUR":{"code":"EUR","symbol":"&euro;","rate":"42,335.16","description":"Euro","rate_float":42335.1604},"CNY":{"code":"CNY","symbol":"&yen;","rate":"329,978.606","description":"Chinese Yuan","rate_float":329978.6061}}}