{"time":{"updated":"Sep 7, 2024 15:42:18 UTC","updatedISO":"2024-09-07T15:42:18+00:00","updateduk":"Sep 7, 2024 at 16:42 BST"},"disclaimer":"This data was produced from the CoinDesk Bitcoin Price Index (USD). Non-USD currency data converted using hourly conversion rate from openexchangerates.org","chartName":"Bitcoin","bpi":{"USD":{"code":"USD","symbol":"&#36;","rate":"54,787.864","description":"United States Dollar","rate_float":54787.8638},"GBP":{"code":"GBP","symbol":"&pound;","rate":"41,720.904","description":"British Pound Sterling","rate_float":41720.9035},"EUR":{"code":"EUR","symbol":"&euro;","rate":"49,402.217","description":"Euro","rate_float":49402.2168},"CNY":{"code":"CNY","symbol":"&yen;","rate":"388,385.688","description":"Chinese Yuan","rate_float":388385.6877}}}