{"time":{"updated":"May 25, 2022 20:00:00 UTC","updatedISO":"2022-05-25T20:00:00+00:00","updateduk":"May 25, 2022 at 21:00 BST"},"disclaimer":"This data was produced from the CoinDesk Bitcoin Price Index (USD). Non-USD currency data converted using hourly conversion rate from openexchangerates.org","chartName":"Bitcoin","bpi":{"USD":{"code":"USD","symbol":"&#36;","rate":"29,555.7660","description":"United States Dollar","rate_float":29555.766},"GBP":{"code":"GBP","symbol":"&pound;","rate":"23,666.3954","description":"British Pound Sterling","rate_float":23666.3954},"EUR":{"code":"EUR","symbol":"&euro;","rate":"27,973.3208","description":"Euro","rate_float":27973.3208},"CNY":{"code":"CNY","symbol":"&yen;","rate":"40,202.5000","description":"Chinese Yuan","rate_float":40202.5}}}