{"time":{"updated":"Apr 15, 2024 13:08:07 UTC","updatedISO":"2024-04-15T13:08:07+00:00","updateduk":"Apr 15, 2024 at 14:08 BST"},"disclaimer":"This data was produced from the CoinDesk Bitcoin Price Index (USD). Non-USD currency data converted using hourly conversion rate from openexchangerates.org","chartName":"Bitcoin","bpi":{"USD":{"code":"USD","symbol":"&#36;","rate":"66,223.004","description":"United States Dollar","rate_float":66223.0036},"GBP":{"code":"GBP","symbol":"&pound;","rate":"53,072.241","description":"British Pound Sterling","rate_float":53072.2409},"EUR":{"code":"EUR","symbol":"&euro;","rate":"62,152.408","description":"Euro","rate_float":62152.408},"CNY":{"code":"CNY","symbol":"&yen;","rate":"479,355.212","description":"Chinese Yuan","rate_float":479355.2118}}}