{"time":{"updated":"Aug 13, 2024 14:49:20 UTC","updatedISO":"2024-08-13T14:49:20+00:00","updateduk":"Aug 13, 2024 at 15:49 BST"},"disclaimer":"This data was produced from the CoinDesk Bitcoin Price Index (USD). Non-USD currency data converted using hourly conversion rate from openexchangerates.org","chartName":"Bitcoin","bpi":{"USD":{"code":"USD","symbol":"&#36;","rate":"59,701.224","description":"United States Dollar","rate_float":59701.2241},"GBP":{"code":"GBP","symbol":"&pound;","rate":"46,575.611","description":"British Pound Sterling","rate_float":46575.6114},"EUR":{"code":"EUR","symbol":"&euro;","rate":"54,477.367","description":"Euro","rate_float":54477.367},"CNY":{"code":"CNY","symbol":"&yen;","rate":"427,150.318","description":"Chinese Yuan","rate_float":427150.318}}}