{"time":{"updated":"Jan 29, 2023 10:07:00 UTC","updatedISO":"2023-01-29T10:07:00+00:00","updateduk":"Jan 29, 2023 at 10:07 GMT"},"disclaimer":"This data was produced from the CoinDesk Bitcoin Price Index (USD). Non-USD currency data converted using hourly conversion rate from openexchangerates.org","chartName":"Bitcoin","bpi":{"USD":{"code":"USD","symbol":"&#36;","rate":"23,388.6124","description":"United States Dollar","rate_float":23388.6124},"GBP":{"code":"GBP","symbol":"&pound;","rate":"19,543.3374","description":"British Pound Sterling","rate_float":19543.3374},"EUR":{"code":"EUR","symbol":"&euro;","rate":"22,783.9232","description":"Euro","rate_float":22783.9232},"CNY":{"code":"CNY","symbol":"&yen;","rate":"40,202.5000","description":"Chinese Yuan","rate_float":40202.5}}}