{"time":{"updated":"Jul 6, 2024 09:57:56 UTC","updatedISO":"2024-07-06T09:57:56+00:00","updateduk":"Jul 6, 2024 at 10:57 BST"},"disclaimer":"This data was produced from the CoinDesk Bitcoin Price Index (USD). Non-USD currency data converted using hourly conversion rate from openexchangerates.org","chartName":"Bitcoin","bpi":{"USD":{"code":"USD","symbol":"&#36;","rate":"56,828.403","description":"United States Dollar","rate_float":56828.4028},"GBP":{"code":"GBP","symbol":"&pound;","rate":"44,365.991","description":"British Pound Sterling","rate_float":44365.9909},"EUR":{"code":"EUR","symbol":"&euro;","rate":"52,389.309","description":"Euro","rate_float":52389.3089},"CNY":{"code":"CNY","symbol":"&yen;","rate":"413,074.294","description":"Chinese Yuan","rate_float":413074.294}}}