{"time":{"updated":"Jan 22, 2025 19:27:48 UTC","updatedISO":"2025-01-22T19:27:48+00:00","updateduk":"Jan 22, 2025 at 19:27 GMT"},"disclaimer":"This data was produced from the CoinDesk Bitcoin Price Index (USD). Non-USD currency data converted using hourly conversion rate from openexchangerates.org","chartName":"Bitcoin","bpi":{"USD":{"code":"USD","symbol":"&#36;","rate":"104,352.562","description":"United States Dollar","rate_float":104352.5615},"GBP":{"code":"GBP","symbol":"&pound;","rate":"83,228.994","description":"British Pound Sterling","rate_float":83228.9942},"EUR":{"code":"EUR","symbol":"&euro;","rate":"100,359.406","description":"Euro","rate_float":100359.4064},"CNY":{"code":"CNY","symbol":"&yen;","rate":"764,685.135","description":"Chinese Yuan","rate_float":764685.1354}}}