{"time":{"updated":"Jan 28, 2025 02:49:26 UTC","updatedISO":"2025-01-28T02:49:26+00:00","updateduk":"Jan 28, 2025 at 02:49 GMT"},"disclaimer":"This data was produced from the CoinDesk Bitcoin Price Index (USD). Non-USD currency data converted using hourly conversion rate from openexchangerates.org","chartName":"Bitcoin","bpi":{"USD":{"code":"USD","symbol":"&#36;","rate":"102,557.748","description":"United States Dollar","rate_float":102557.7477},"GBP":{"code":"GBP","symbol":"&pound;","rate":"82,362.794","description":"British Pound Sterling","rate_float":82362.7939},"EUR":{"code":"EUR","symbol":"&euro;","rate":"98,053.104","description":"Euro","rate_float":98053.1038},"CNY":{"code":"CNY","symbol":"&yen;","rate":"745,256.385","description":"Chinese Yuan","rate_float":745256.3854}}}