{"time":{"updated":"May 28, 2024 03:50:43 UTC","updatedISO":"2024-05-28T03:50:43+00:00","updateduk":"May 28, 2024 at 04:50 BST"},"disclaimer":"This data was produced from the CoinDesk Bitcoin Price Index (USD). Non-USD currency data converted using hourly conversion rate from openexchangerates.org","chartName":"Bitcoin","bpi":{"USD":{"code":"USD","symbol":"&#36;","rate":"67,815.75","description":"United States Dollar","rate_float":67815.7496},"GBP":{"code":"GBP","symbol":"&pound;","rate":"53,056.533","description":"British Pound Sterling","rate_float":53056.5333},"EUR":{"code":"EUR","symbol":"&euro;","rate":"62,354.276","description":"Euro","rate_float":62354.276},"CNY":{"code":"CNY","symbol":"&yen;","rate":"481,986.877","description":"Chinese Yuan","rate_float":481986.8769}}}