{"time":{"updated":"Jan 18, 2025 09:53:24 UTC","updatedISO":"2025-01-18T09:53:24+00:00","updateduk":"Jan 18, 2025 at 09:53 GMT"},"disclaimer":"This data was produced from the CoinDesk Bitcoin Price Index (USD). Non-USD currency data converted using hourly conversion rate from openexchangerates.org","chartName":"Bitcoin","bpi":{"USD":{"code":"USD","symbol":"&#36;","rate":"104,027.712","description":"United States Dollar","rate_float":104027.7117},"GBP":{"code":"GBP","symbol":"&pound;","rate":"82,969.902","description":"British Pound Sterling","rate_float":82969.9022},"EUR":{"code":"EUR","symbol":"&euro;","rate":"100,046.987","description":"Euro","rate_float":100046.9873},"CNY":{"code":"CNY","symbol":"&yen;","rate":"762,304.669","description":"Chinese Yuan","rate_float":762304.6688}}}