{"time":{"updated":"Oct 12, 2024 17:56:38 UTC","updatedISO":"2024-10-12T17:56:38+00:00","updateduk":"Oct 12, 2024 at 18:56 BST"},"disclaimer":"This data was produced from the CoinDesk Bitcoin Price Index (USD). Non-USD currency data converted using hourly conversion rate from openexchangerates.org","chartName":"Bitcoin","bpi":{"USD":{"code":"USD","symbol":"&#36;","rate":"63,083.399","description":"United States Dollar","rate_float":63083.3987},"GBP":{"code":"GBP","symbol":"&pound;","rate":"48,269.461","description":"British Pound Sterling","rate_float":48269.4611},"EUR":{"code":"EUR","symbol":"&euro;","rate":"57,646.682","description":"Euro","rate_float":57646.6822},"CNY":{"code":"CNY","symbol":"&yen;","rate":"445,759.912","description":"Chinese Yuan","rate_float":445759.912}}}