{"time":{"updated":"Oct 30, 2024 23:27:33 UTC","updatedISO":"2024-10-30T23:27:33+00:00","updateduk":"Oct 30, 2024 at 23:27 GMT"},"disclaimer":"This data was produced from the CoinDesk Bitcoin Price Index (USD). Non-USD currency data converted using hourly conversion rate from openexchangerates.org","chartName":"Bitcoin","bpi":{"USD":{"code":"USD","symbol":"&#36;","rate":"72,583.008","description":"United States Dollar","rate_float":72583.0076},"GBP":{"code":"GBP","symbol":"&pound;","rate":"56,016.299","description":"British Pound Sterling","rate_float":56016.299},"EUR":{"code":"EUR","symbol":"&euro;","rate":"66,843.071","description":"Euro","rate_float":66843.0708},"CNY":{"code":"CNY","symbol":"&yen;","rate":"516,471.649","description":"Chinese Yuan","rate_float":516471.649}}}