{"time":{"updated":"Mar 2, 2024 08:26:12 UTC","updatedISO":"2024-03-02T08:26:12+00:00","updateduk":"Mar 2, 2024 at 08:26 GMT"},"disclaimer":"This data was produced from the CoinDesk Bitcoin Price Index (USD). Non-USD currency data converted using hourly conversion rate from openexchangerates.org","chartName":"Bitcoin","bpi":{"USD":{"code":"USD","symbol":"&#36;","rate":"61,910.451","description":"United States Dollar","rate_float":61910.4508},"GBP":{"code":"GBP","symbol":"&pound;","rate":"48,914.023","description":"British Pound Sterling","rate_float":48914.0232},"EUR":{"code":"EUR","symbol":"&euro;","rate":"57,084.531","description":"Euro","rate_float":57084.5311},"CNY":{"code":"CNY","symbol":"&yen;","rate":"445,532.368","description":"Chinese Yuan","rate_float":445532.3678}}}