{"time":{"updated":"Jun 13, 2024 10:59:03 UTC","updatedISO":"2024-06-13T10:59:03+00:00","updateduk":"Jun 13, 2024 at 11:59 BST"},"disclaimer":"This data was produced from the CoinDesk Bitcoin Price Index (USD). Non-USD currency data converted using hourly conversion rate from openexchangerates.org","chartName":"Bitcoin","bpi":{"USD":{"code":"USD","symbol":"&#36;","rate":"67,915.127","description":"United States Dollar","rate_float":67915.1269},"GBP":{"code":"GBP","symbol":"&pound;","rate":"53,127.898","description":"British Pound Sterling","rate_float":53127.8984},"EUR":{"code":"EUR","symbol":"&euro;","rate":"62,872.904","description":"Euro","rate_float":62872.9042},"CNY":{"code":"CNY","symbol":"&yen;","rate":"492,561.25","description":"Chinese Yuan","rate_float":492561.2497}}}