{"time":{"updated":"May 19, 2023 06:40:00 UTC","updatedISO":"2023-05-19T06:40:00+00:00","updateduk":"May 19, 2023 at 07:40 BST"},"disclaimer":"This data was produced from the CoinDesk Bitcoin Price Index (USD). Non-USD currency data converted using hourly conversion rate from openexchangerates.org","chartName":"Bitcoin","bpi":{"USD":{"code":"USD","symbol":"&#36;","rate":"26,876.0154","description":"United States Dollar","rate_float":26876.0154},"GBP":{"code":"GBP","symbol":"&pound;","rate":"22,457.3835","description":"British Pound Sterling","rate_float":22457.3835},"EUR":{"code":"EUR","symbol":"&euro;","rate":"26,181.1629","description":"Euro","rate_float":26181.1629},"CNY":{"code":"CNY","symbol":"&yen;","rate":"40,202.5000","description":"Chinese Yuan","rate_float":40202.5}}}