{"time":{"updated":"Jan 16, 2024 13:48:08 UTC","updatedISO":"2024-01-16T13:48:08+00:00","updateduk":"Jan 16, 2024 at 13:48 GMT"},"disclaimer":"This data was produced from the CoinDesk Bitcoin Price Index (USD). Non-USD currency data converted using hourly conversion rate from openexchangerates.org","chartName":"Bitcoin","bpi":{"USD":{"code":"USD","symbol":"&#36;","rate":"42,928.354","description":"United States Dollar","rate_float":42928.3541},"GBP":{"code":"GBP","symbol":"&pound;","rate":"33,943.493","description":"British Pound Sterling","rate_float":33943.4925},"EUR":{"code":"EUR","symbol":"&euro;","rate":"39,434.244","description":"Euro","rate_float":39434.2436},"CNY":{"code":"CNY","symbol":"&yen;","rate":"305,941.794","description":"Chinese Yuan","rate_float":305941.794}}}