{"time":{"updated":"Jul 28, 2022 16:50:00 UTC","updatedISO":"2022-07-28T16:50:00+00:00","updateduk":"Jul 28, 2022 at 17:50 BST"},"disclaimer":"This data was produced from the CoinDesk Bitcoin Price Index (USD). Non-USD currency data converted using hourly conversion rate from openexchangerates.org","chartName":"Bitcoin","bpi":{"USD":{"code":"USD","symbol":"&#36;","rate":"23,810.1238","description":"United States Dollar","rate_float":23810.1238},"GBP":{"code":"GBP","symbol":"&pound;","rate":"19,895.5489","description":"British Pound Sterling","rate_float":19895.5489},"EUR":{"code":"EUR","symbol":"&euro;","rate":"23,194.5368","description":"Euro","rate_float":23194.5368},"CNY":{"code":"CNY","symbol":"&yen;","rate":"40,202.5000","description":"Chinese Yuan","rate_float":40202.5}}}