{"time":{"updated":"Sep 19, 2024 22:40:33 UTC","updatedISO":"2024-09-19T22:40:33+00:00","updateduk":"Sep 19, 2024 at 23:40 BST"},"disclaimer":"This data was produced from the CoinDesk Bitcoin Price Index (USD). Non-USD currency data converted using hourly conversion rate from openexchangerates.org","chartName":"Bitcoin","bpi":{"USD":{"code":"USD","symbol":"&#36;","rate":"62,884.15","description":"United States Dollar","rate_float":62884.1504},"GBP":{"code":"GBP","symbol":"&pound;","rate":"47,337.302","description":"British Pound Sterling","rate_float":47337.3019},"EUR":{"code":"EUR","symbol":"&euro;","rate":"56,336.841","description":"Euro","rate_float":56336.8413},"CNY":{"code":"CNY","symbol":"&yen;","rate":"444,465.175","description":"Chinese Yuan","rate_float":444465.1747}}}