{"time":{"updated":"Dec 9, 2022 13:57:00 UTC","updatedISO":"2022-12-09T13:57:00+00:00","updateduk":"Dec 9, 2022 at 13:57 GMT"},"disclaimer":"This data was produced from the CoinDesk Bitcoin Price Index (USD). Non-USD currency data converted using hourly conversion rate from openexchangerates.org","chartName":"Bitcoin","bpi":{"USD":{"code":"USD","symbol":"&#36;","rate":"17,177.2288","description":"United States Dollar","rate_float":17177.2288},"GBP":{"code":"GBP","symbol":"&pound;","rate":"14,353.1550","description":"British Pound Sterling","rate_float":14353.155},"EUR":{"code":"EUR","symbol":"&euro;","rate":"16,733.1287","description":"Euro","rate_float":16733.1287},"CNY":{"code":"CNY","symbol":"&yen;","rate":"40,202.5000","description":"Chinese Yuan","rate_float":40202.5}}}