{"time":{"updated":"Dec 1, 2024 23:41:57 UTC","updatedISO":"2024-12-01T23:41:57+00:00","updateduk":"Dec 1, 2024 at 23:41 GMT"},"disclaimer":"This data was produced from the CoinDesk Bitcoin Price Index (USD). Non-USD currency data converted using hourly conversion rate from openexchangerates.org","chartName":"Bitcoin","bpi":{"USD":{"code":"USD","symbol":"&#36;","rate":"97,518.144","description":"United States Dollar","rate_float":97518.1441},"GBP":{"code":"GBP","symbol":"&pound;","rate":"76,596.211","description":"British Pound Sterling","rate_float":76596.2114},"EUR":{"code":"EUR","symbol":"&euro;","rate":"92,309.798","description":"Euro","rate_float":92309.7975},"CNY":{"code":"CNY","symbol":"&yen;","rate":"706,197.144","description":"Chinese Yuan","rate_float":706197.1441}}}