{"time":{"updated":"Aug 16, 2024 03:00:11 UTC","updatedISO":"2024-08-16T03:00:11+00:00","updateduk":"Aug 16, 2024 at 04:00 BST"},"disclaimer":"This data was produced from the CoinDesk Bitcoin Price Index (USD). Non-USD currency data converted using hourly conversion rate from openexchangerates.org","chartName":"Bitcoin","bpi":{"USD":{"code":"USD","symbol":"&#36;","rate":"58,212.923","description":"United States Dollar","rate_float":58212.9229},"GBP":{"code":"GBP","symbol":"&pound;","rate":"45,225.096","description":"British Pound Sterling","rate_float":45225.0959},"EUR":{"code":"EUR","symbol":"&euro;","rate":"53,012.821","description":"Euro","rate_float":53012.8207},"CNY":{"code":"CNY","symbol":"&yen;","rate":"417,171.269","description":"Chinese Yuan","rate_float":417171.2694}}}