{"time":{"updated":"Apr 1, 2024 19:45:24 UTC","updatedISO":"2024-04-01T19:45:24+00:00","updateduk":"Apr 1, 2024 at 20:45 BST"},"disclaimer":"This data was produced from the CoinDesk Bitcoin Price Index (USD). Non-USD currency data converted using hourly conversion rate from openexchangerates.org","chartName":"Bitcoin","bpi":{"USD":{"code":"USD","symbol":"&#36;","rate":"69,338.091","description":"United States Dollar","rate_float":69338.0914},"GBP":{"code":"GBP","symbol":"&pound;","rate":"55,280.695","description":"British Pound Sterling","rate_float":55280.6948},"EUR":{"code":"EUR","symbol":"&euro;","rate":"64,574.842","description":"Euro","rate_float":64574.8419},"CNY":{"code":"CNY","symbol":"&yen;","rate":"501,369.872","description":"Chinese Yuan","rate_float":501369.8716}}}