{"time":{"updated":"Jan 13, 2025 05:43:08 UTC","updatedISO":"2025-01-13T05:43:08+00:00","updateduk":"Jan 13, 2025 at 05:43 GMT"},"disclaimer":"This data was produced from the CoinDesk Bitcoin Price Index (USD). Non-USD currency data converted using hourly conversion rate from openexchangerates.org","chartName":"Bitcoin","bpi":{"USD":{"code":"USD","symbol":"&#36;","rate":"95,748.894","description":"United States Dollar","rate_float":95748.8939},"GBP":{"code":"GBP","symbol":"&pound;","rate":"76,366.924","description":"British Pound Sterling","rate_float":76366.924},"EUR":{"code":"EUR","symbol":"&euro;","rate":"92,084.967","description":"Euro","rate_float":92084.9667},"CNY":{"code":"CNY","symbol":"&yen;","rate":"701,638.32","description":"Chinese Yuan","rate_float":701638.3195}}}