{"time":{"updated":"Mar 26, 2024 22:36:47 UTC","updatedISO":"2024-03-26T22:36:47+00:00","updateduk":"Mar 26, 2024 at 22:36 GMT"},"disclaimer":"This data was produced from the CoinDesk Bitcoin Price Index (USD). Non-USD currency data converted using hourly conversion rate from openexchangerates.org","chartName":"Bitcoin","bpi":{"USD":{"code":"USD","symbol":"&#36;","rate":"69,987.254","description":"United States Dollar","rate_float":69987.2538},"GBP":{"code":"GBP","symbol":"&pound;","rate":"55,416.118","description":"British Pound Sterling","rate_float":55416.1175},"EUR":{"code":"EUR","symbol":"&euro;","rate":"64,604.954","description":"Euro","rate_float":64604.954},"CNY":{"code":"CNY","symbol":"&yen;","rate":"505,181.995","description":"Chinese Yuan","rate_float":505181.9951}}}