{"time":{"updated":"Jan 11, 2025 08:34:48 UTC","updatedISO":"2025-01-11T08:34:48+00:00","updateduk":"Jan 11, 2025 at 08:34 GMT"},"disclaimer":"This data was produced from the CoinDesk Bitcoin Price Index (USD). Non-USD currency data converted using hourly conversion rate from openexchangerates.org","chartName":"Bitcoin","bpi":{"USD":{"code":"USD","symbol":"&#36;","rate":"95,626.722","description":"United States Dollar","rate_float":95626.7216},"GBP":{"code":"GBP","symbol":"&pound;","rate":"76,269.482","description":"British Pound Sterling","rate_float":76269.4824},"EUR":{"code":"EUR","symbol":"&euro;","rate":"91,967.469","description":"Euro","rate_float":91967.4694},"CNY":{"code":"CNY","symbol":"&yen;","rate":"700,743.053","description":"Chinese Yuan","rate_float":700743.0529}}}