{"time":{"updated":"Jul 22, 2024 16:40:14 UTC","updatedISO":"2024-07-22T16:40:14+00:00","updateduk":"Jul 22, 2024 at 17:40 BST"},"disclaimer":"This data was produced from the CoinDesk Bitcoin Price Index (USD). Non-USD currency data converted using hourly conversion rate from openexchangerates.org","chartName":"Bitcoin","bpi":{"USD":{"code":"USD","symbol":"&#36;","rate":"66,971.164","description":"United States Dollar","rate_float":66971.164},"GBP":{"code":"GBP","symbol":"&pound;","rate":"51,881.556","description":"British Pound Sterling","rate_float":51881.5562},"EUR":{"code":"EUR","symbol":"&euro;","rate":"61,555.072","description":"Euro","rate_float":61555.072},"CNY":{"code":"CNY","symbol":"&yen;","rate":"486,994.213","description":"Chinese Yuan","rate_float":486994.213}}}