{"time":{"updated":"Jan 21, 2025 14:36:29 UTC","updatedISO":"2025-01-21T14:36:29+00:00","updateduk":"Jan 21, 2025 at 14:36 GMT"},"disclaimer":"This data was produced from the CoinDesk Bitcoin Price Index (USD). Non-USD currency data converted using hourly conversion rate from openexchangerates.org","chartName":"Bitcoin","bpi":{"USD":{"code":"USD","symbol":"&#36;","rate":"103,819.236","description":"United States Dollar","rate_float":103819.236},"GBP":{"code":"GBP","symbol":"&pound;","rate":"82,803.627","description":"British Pound Sterling","rate_float":82803.6272},"EUR":{"code":"EUR","symbol":"&euro;","rate":"99,846.489","description":"Euro","rate_float":99846.4891},"CNY":{"code":"CNY","symbol":"&yen;","rate":"760,776.98","description":"Chinese Yuan","rate_float":760776.9797}}}