{"time":{"updated":"Jul 5, 2024 07:18:26 UTC","updatedISO":"2024-07-05T07:18:26+00:00","updateduk":"Jul 5, 2024 at 08:18 BST"},"disclaimer":"This data was produced from the CoinDesk Bitcoin Price Index (USD). Non-USD currency data converted using hourly conversion rate from openexchangerates.org","chartName":"Bitcoin","bpi":{"USD":{"code":"USD","symbol":"&#36;","rate":"54,385.825","description":"United States Dollar","rate_float":54385.8247},"GBP":{"code":"GBP","symbol":"&pound;","rate":"42,587.962","description":"British Pound Sterling","rate_float":42587.9621},"EUR":{"code":"EUR","symbol":"&euro;","rate":"50,268.383","description":"Euro","rate_float":50268.3826},"CNY":{"code":"CNY","symbol":"&yen;","rate":"395,297.928","description":"Chinese Yuan","rate_float":395297.9279}}}