{"time":{"updated":"May 9, 2024 06:37:16 UTC","updatedISO":"2024-05-09T06:37:16+00:00","updateduk":"May 9, 2024 at 07:37 BST"},"disclaimer":"This data was produced from the CoinDesk Bitcoin Price Index (USD). Non-USD currency data converted using hourly conversion rate from openexchangerates.org","chartName":"Bitcoin","bpi":{"USD":{"code":"USD","symbol":"&#36;","rate":"61,659.073","description":"United States Dollar","rate_float":61659.0732},"GBP":{"code":"GBP","symbol":"&pound;","rate":"49,365.549","description":"British Pound Sterling","rate_float":49365.5488},"EUR":{"code":"EUR","symbol":"&euro;","rate":"57,388.812","description":"Euro","rate_float":57388.8124},"CNY":{"code":"CNY","symbol":"&yen;","rate":"445,499.136","description":"Chinese Yuan","rate_float":445499.1356}}}