{"time":{"updated":"May 25, 2024 06:44:52 UTC","updatedISO":"2024-05-25T06:44:52+00:00","updateduk":"May 25, 2024 at 07:44 BST"},"disclaimer":"This data was produced from the CoinDesk Bitcoin Price Index (USD). Non-USD currency data converted using hourly conversion rate from openexchangerates.org","chartName":"Bitcoin","bpi":{"USD":{"code":"USD","symbol":"&#36;","rate":"68,717.933","description":"United States Dollar","rate_float":68717.9329},"GBP":{"code":"GBP","symbol":"&pound;","rate":"53,930.246","description":"British Pound Sterling","rate_float":53930.2461},"EUR":{"code":"EUR","symbol":"&euro;","rate":"63,314.092","description":"Euro","rate_float":63314.0921},"CNY":{"code":"CNY","symbol":"&yen;","rate":"488,660.093","description":"Chinese Yuan","rate_float":488660.0928}}}