{"time":{"updated":"Jun 29, 2024 22:18:52 UTC","updatedISO":"2024-06-29T22:18:52+00:00","updateduk":"Jun 29, 2024 at 23:18 BST"},"disclaimer":"This data was produced from the CoinDesk Bitcoin Price Index (USD). Non-USD currency data converted using hourly conversion rate from openexchangerates.org","chartName":"Bitcoin","bpi":{"USD":{"code":"USD","symbol":"&#36;","rate":"60,951.531","description":"United States Dollar","rate_float":60951.5309},"GBP":{"code":"GBP","symbol":"&pound;","rate":"48,186.818","description":"British Pound Sterling","rate_float":48186.8175},"EUR":{"code":"EUR","symbol":"&euro;","rate":"56,856.868","description":"Euro","rate_float":56856.868},"CNY":{"code":"CNY","symbol":"&yen;","rate":"442,953.061","description":"Chinese Yuan","rate_float":442953.0605}}}