{"time":{"updated":"Aug 18, 2024 05:57:59 UTC","updatedISO":"2024-08-18T05:57:59+00:00","updateduk":"Aug 18, 2024 at 06:57 BST"},"disclaimer":"This data was produced from the CoinDesk Bitcoin Price Index (USD). Non-USD currency data converted using hourly conversion rate from openexchangerates.org","chartName":"Bitcoin","bpi":{"USD":{"code":"USD","symbol":"&#36;","rate":"59,524.644","description":"United States Dollar","rate_float":59524.6438},"GBP":{"code":"GBP","symbol":"&pound;","rate":"45,988.085","description":"British Pound Sterling","rate_float":45988.085},"EUR":{"code":"EUR","symbol":"&euro;","rate":"53,958.792","description":"Euro","rate_float":53958.792},"CNY":{"code":"CNY","symbol":"&yen;","rate":"426,494.073","description":"Chinese Yuan","rate_float":426494.0727}}}