{"time":{"updated":"Aug 27, 2024 08:24:23 UTC","updatedISO":"2024-08-27T08:24:23+00:00","updateduk":"Aug 27, 2024 at 09:24 BST"},"disclaimer":"This data was produced from the CoinDesk Bitcoin Price Index (USD). Non-USD currency data converted using hourly conversion rate from openexchangerates.org","chartName":"Bitcoin","bpi":{"USD":{"code":"USD","symbol":"&#36;","rate":"62,773.455","description":"United States Dollar","rate_float":62773.4546},"GBP":{"code":"GBP","symbol":"&pound;","rate":"47,577.822","description":"British Pound Sterling","rate_float":47577.8216},"EUR":{"code":"EUR","symbol":"&euro;","rate":"56,237.545","description":"Euro","rate_float":56237.5452},"CNY":{"code":"CNY","symbol":"&yen;","rate":"447,122.762","description":"Chinese Yuan","rate_float":447122.7621}}}