{"time":{"updated":"Dec 7, 2024 05:39:04 UTC","updatedISO":"2024-12-07T05:39:04+00:00","updateduk":"Dec 7, 2024 at 05:39 GMT"},"disclaimer":"This data was produced from the CoinDesk Bitcoin Price Index (USD). Non-USD currency data converted using hourly conversion rate from openexchangerates.org","chartName":"Bitcoin","bpi":{"USD":{"code":"USD","symbol":"&#36;","rate":"99,360.637","description":"United States Dollar","rate_float":99360.6367},"GBP":{"code":"GBP","symbol":"&pound;","rate":"77,960.442","description":"British Pound Sterling","rate_float":77960.4421},"EUR":{"code":"EUR","symbol":"&euro;","rate":"93,952.537","description":"Euro","rate_float":93952.5366},"CNY":{"code":"CNY","symbol":"&yen;","rate":"722,381.637","description":"Chinese Yuan","rate_float":722381.6372}}}