{"time":{"updated":"Mar 2, 2024 16:27:52 UTC","updatedISO":"2024-03-02T16:27:52+00:00","updateduk":"Mar 2, 2024 at 16:27 GMT"},"disclaimer":"This data was produced from the CoinDesk Bitcoin Price Index (USD). Non-USD currency data converted using hourly conversion rate from openexchangerates.org","chartName":"Bitcoin","bpi":{"USD":{"code":"USD","symbol":"&#36;","rate":"61,824.592","description":"United States Dollar","rate_float":61824.5919},"GBP":{"code":"GBP","symbol":"&pound;","rate":"48,846.188","description":"British Pound Sterling","rate_float":48846.1881},"EUR":{"code":"EUR","symbol":"&euro;","rate":"57,005.365","description":"Euro","rate_float":57005.365},"CNY":{"code":"CNY","symbol":"&yen;","rate":"444,914.493","description":"Chinese Yuan","rate_float":444914.4931}}}