{"time":{"updated":"Jun 7, 2024 03:35:21 UTC","updatedISO":"2024-06-07T03:35:21+00:00","updateduk":"Jun 7, 2024 at 04:35 BST"},"disclaimer":"This data was produced from the CoinDesk Bitcoin Price Index (USD). Non-USD currency data converted using hourly conversion rate from openexchangerates.org","chartName":"Bitcoin","bpi":{"USD":{"code":"USD","symbol":"&#36;","rate":"70,940.987","description":"United States Dollar","rate_float":70940.9867},"GBP":{"code":"GBP","symbol":"&pound;","rate":"55,467.693","description":"British Pound Sterling","rate_float":55467.6933},"EUR":{"code":"EUR","symbol":"&euro;","rate":"65,106.091","description":"Euro","rate_float":65106.0905},"CNY":{"code":"CNY","symbol":"&yen;","rate":"514,017.107","description":"Chinese Yuan","rate_float":514017.107}}}