{"time":{"updated":"Jul 18, 2024 11:33:27 UTC","updatedISO":"2024-07-18T11:33:27+00:00","updateduk":"Jul 18, 2024 at 12:33 BST"},"disclaimer":"This data was produced from the CoinDesk Bitcoin Price Index (USD). Non-USD currency data converted using hourly conversion rate from openexchangerates.org","chartName":"Bitcoin","bpi":{"USD":{"code":"USD","symbol":"&#36;","rate":"64,691.862","description":"United States Dollar","rate_float":64691.8617},"GBP":{"code":"GBP","symbol":"&pound;","rate":"49,796.884","description":"British Pound Sterling","rate_float":49796.884},"EUR":{"code":"EUR","symbol":"&euro;","rate":"59,171.446","description":"Euro","rate_float":59171.4464},"CNY":{"code":"CNY","symbol":"&yen;","rate":"469,675.855","description":"Chinese Yuan","rate_float":469675.8545}}}