{"time":{"updated":"Dec 4, 2022 09:07:00 UTC","updatedISO":"2022-12-04T09:07:00+00:00","updateduk":"Dec 4, 2022 at 09:07 GMT"},"disclaimer":"This data was produced from the CoinDesk Bitcoin Price Index (USD). Non-USD currency data converted using hourly conversion rate from openexchangerates.org","chartName":"Bitcoin","bpi":{"USD":{"code":"USD","symbol":"&#36;","rate":"17,027.6918","description":"United States Dollar","rate_float":17027.6918},"GBP":{"code":"GBP","symbol":"&pound;","rate":"14,228.2030","description":"British Pound Sterling","rate_float":14228.203},"EUR":{"code":"EUR","symbol":"&euro;","rate":"16,587.4578","description":"Euro","rate_float":16587.4578},"CNY":{"code":"CNY","symbol":"&yen;","rate":"40,202.5000","description":"Chinese Yuan","rate_float":40202.5}}}