{"time":{"updated":"Jan 21, 2025 13:38:55 UTC","updatedISO":"2025-01-21T13:38:55+00:00","updateduk":"Jan 21, 2025 at 13:38 GMT"},"disclaimer":"This data was produced from the CoinDesk Bitcoin Price Index (USD). Non-USD currency data converted using hourly conversion rate from openexchangerates.org","chartName":"Bitcoin","bpi":{"USD":{"code":"USD","symbol":"&#36;","rate":"104,854.834","description":"United States Dollar","rate_float":104854.8335},"GBP":{"code":"GBP","symbol":"&pound;","rate":"83,629.594","description":"British Pound Sterling","rate_float":83629.5938},"EUR":{"code":"EUR","symbol":"&euro;","rate":"100,842.459","description":"Euro","rate_float":100842.4585},"CNY":{"code":"CNY","symbol":"&yen;","rate":"768,365.735","description":"Chinese Yuan","rate_float":768365.7345}}}