{"time":{"updated":"Jul 9, 2024 16:53:33 UTC","updatedISO":"2024-07-09T16:53:33+00:00","updateduk":"Jul 9, 2024 at 17:53 BST"},"disclaimer":"This data was produced from the CoinDesk Bitcoin Price Index (USD). Non-USD currency data converted using hourly conversion rate from openexchangerates.org","chartName":"Bitcoin","bpi":{"USD":{"code":"USD","symbol":"&#36;","rate":"57,592.254","description":"United States Dollar","rate_float":57592.2536},"GBP":{"code":"GBP","symbol":"&pound;","rate":"45,046.012","description":"British Pound Sterling","rate_float":45046.0116},"EUR":{"code":"EUR","symbol":"&euro;","rate":"53,264.023","description":"Euro","rate_float":53264.023},"CNY":{"code":"CNY","symbol":"&yen;","rate":"418,839.665","description":"Chinese Yuan","rate_float":418839.6646}}}