{"time":{"updated":"Aug 26, 2024 11:11:02 UTC","updatedISO":"2024-08-26T11:11:02+00:00","updateduk":"Aug 26, 2024 at 12:11 BST"},"disclaimer":"This data was produced from the CoinDesk Bitcoin Price Index (USD). Non-USD currency data converted using hourly conversion rate from openexchangerates.org","chartName":"Bitcoin","bpi":{"USD":{"code":"USD","symbol":"&#36;","rate":"63,966.793","description":"United States Dollar","rate_float":63966.7933},"GBP":{"code":"GBP","symbol":"&pound;","rate":"48,499.175","description":"British Pound Sterling","rate_float":48499.1749},"EUR":{"code":"EUR","symbol":"&euro;","rate":"57,244.715","description":"Euro","rate_float":57244.7148},"CNY":{"code":"CNY","symbol":"&yen;","rate":"455,290.048","description":"Chinese Yuan","rate_float":455290.0476}}}