{"time":{"updated":"Aug 7, 2024 08:55:32 UTC","updatedISO":"2024-08-07T08:55:32+00:00","updateduk":"Aug 7, 2024 at 09:55 BST"},"disclaimer":"This data was produced from the CoinDesk Bitcoin Price Index (USD). Non-USD currency data converted using hourly conversion rate from openexchangerates.org","chartName":"Bitcoin","bpi":{"USD":{"code":"USD","symbol":"&#36;","rate":"57,408.96","description":"United States Dollar","rate_float":57408.96},"GBP":{"code":"GBP","symbol":"&pound;","rate":"45,209.326","description":"British Pound Sterling","rate_float":45209.3264},"EUR":{"code":"EUR","symbol":"&euro;","rate":"52,562.094","description":"Euro","rate_float":52562.0937},"CNY":{"code":"CNY","symbol":"&yen;","rate":"412,270.965","description":"Chinese Yuan","rate_float":412270.9645}}}