{"time":{"updated":"Jul 30, 2024 09:47:05 UTC","updatedISO":"2024-07-30T09:47:05+00:00","updateduk":"Jul 30, 2024 at 10:47 BST"},"disclaimer":"This data was produced from the CoinDesk Bitcoin Price Index (USD). Non-USD currency data converted using hourly conversion rate from openexchangerates.org","chartName":"Bitcoin","bpi":{"USD":{"code":"USD","symbol":"&#36;","rate":"66,640.632","description":"United States Dollar","rate_float":66640.6321},"GBP":{"code":"GBP","symbol":"&pound;","rate":"51,821.155","description":"British Pound Sterling","rate_float":51821.1549},"EUR":{"code":"EUR","symbol":"&euro;","rate":"61,539.758","description":"Euro","rate_float":61539.7582},"CNY":{"code":"CNY","symbol":"&yen;","rate":"483,151.247","description":"Chinese Yuan","rate_float":483151.2465}}}