{"time":{"updated":"Jul 5, 2024 04:32:23 UTC","updatedISO":"2024-07-05T04:32:23+00:00","updateduk":"Jul 5, 2024 at 05:32 BST"},"disclaimer":"This data was produced from the CoinDesk Bitcoin Price Index (USD). Non-USD currency data converted using hourly conversion rate from openexchangerates.org","chartName":"Bitcoin","bpi":{"USD":{"code":"USD","symbol":"&#36;","rate":"54,462.407","description":"United States Dollar","rate_float":54462.4068},"GBP":{"code":"GBP","symbol":"&pound;","rate":"42,648.694","description":"British Pound Sterling","rate_float":42648.6938},"EUR":{"code":"EUR","symbol":"&euro;","rate":"50,326.096","description":"Euro","rate_float":50326.0959},"CNY":{"code":"CNY","symbol":"&yen;","rate":"395,860.004","description":"Chinese Yuan","rate_float":395860.0035}}}