{"time":{"updated":"Jan 15, 2025 08:27:04 UTC","updatedISO":"2025-01-15T08:27:04+00:00","updateduk":"Jan 15, 2025 at 08:27 GMT"},"disclaimer":"This data was produced from the CoinDesk Bitcoin Price Index (USD). Non-USD currency data converted using hourly conversion rate from openexchangerates.org","chartName":"Bitcoin","bpi":{"USD":{"code":"USD","symbol":"&#36;","rate":"98,297.039","description":"United States Dollar","rate_float":98297.0388},"GBP":{"code":"GBP","symbol":"&pound;","rate":"78,399.261","description":"British Pound Sterling","rate_float":78399.2607},"EUR":{"code":"EUR","symbol":"&euro;","rate":"94,535.604","description":"Euro","rate_float":94535.6043},"CNY":{"code":"CNY","symbol":"&yen;","rate":"720,310.87","description":"Chinese Yuan","rate_float":720310.8703}}}