{"time":{"updated":"Aug 16, 2024 17:59:52 UTC","updatedISO":"2024-08-16T17:59:52+00:00","updateduk":"Aug 16, 2024 at 18:59 BST"},"disclaimer":"This data was produced from the CoinDesk Bitcoin Price Index (USD). Non-USD currency data converted using hourly conversion rate from openexchangerates.org","chartName":"Bitcoin","bpi":{"USD":{"code":"USD","symbol":"&#36;","rate":"59,259.442","description":"United States Dollar","rate_float":59259.4421},"GBP":{"code":"GBP","symbol":"&pound;","rate":"45,866.867","description":"British Pound Sterling","rate_float":45866.8674},"EUR":{"code":"EUR","symbol":"&euro;","rate":"53,854.388","description":"Euro","rate_float":53854.3883},"CNY":{"code":"CNY","symbol":"&yen;","rate":"424,587.976","description":"Chinese Yuan","rate_float":424587.9764}}}