{"time":{"updated":"Mar 4, 2024 04:51:09 UTC","updatedISO":"2024-03-04T04:51:09+00:00","updateduk":"Mar 4, 2024 at 04:51 GMT"},"disclaimer":"This data was produced from the CoinDesk Bitcoin Price Index (USD). Non-USD currency data converted using hourly conversion rate from openexchangerates.org","chartName":"Bitcoin","bpi":{"USD":{"code":"USD","symbol":"&#36;","rate":"63,592.147","description":"United States Dollar","rate_float":63592.1471},"GBP":{"code":"GBP","symbol":"&pound;","rate":"50,215.539","description":"British Pound Sterling","rate_float":50215.5389},"EUR":{"code":"EUR","symbol":"&euro;","rate":"58,642.961","description":"Euro","rate_float":58642.961},"CNY":{"code":"CNY","symbol":"&yen;","rate":"457,774.43","description":"Chinese Yuan","rate_float":457774.4299}}}