{"time":{"updated":"Jun 8, 2024 08:36:06 UTC","updatedISO":"2024-06-08T08:36:06+00:00","updateduk":"Jun 8, 2024 at 09:36 BST"},"disclaimer":"This data was produced from the CoinDesk Bitcoin Price Index (USD). Non-USD currency data converted using hourly conversion rate from openexchangerates.org","chartName":"Bitcoin","bpi":{"USD":{"code":"USD","symbol":"&#36;","rate":"69,540.961","description":"United States Dollar","rate_float":69540.9606},"GBP":{"code":"GBP","symbol":"&pound;","rate":"54,636.177","description":"British Pound Sterling","rate_float":54636.177},"EUR":{"code":"EUR","symbol":"&euro;","rate":"64,346.251","description":"Euro","rate_float":64346.2508},"CNY":{"code":"CNY","symbol":"&yen;","rate":"503,893.801","description":"Chinese Yuan","rate_float":503893.8005}}}