{"time":{"updated":"Jul 22, 2024 23:59:05 UTC","updatedISO":"2024-07-22T23:59:05+00:00","updateduk":"Jul 23, 2024 at 00:59 BST"},"disclaimer":"This data was produced from the CoinDesk Bitcoin Price Index (USD). Non-USD currency data converted using hourly conversion rate from openexchangerates.org","chartName":"Bitcoin","bpi":{"USD":{"code":"USD","symbol":"&#36;","rate":"67,629.081","description":"United States Dollar","rate_float":67629.0813},"GBP":{"code":"GBP","symbol":"&pound;","rate":"52,287.83","description":"British Pound Sterling","rate_float":52287.83},"EUR":{"code":"EUR","symbol":"&euro;","rate":"62,096.008","description":"Euro","rate_float":62096.008},"CNY":{"code":"CNY","symbol":"&yen;","rate":"491,913.649","description":"Chinese Yuan","rate_float":491913.6487}}}