{"time":{"updated":"Jan 8, 2025 04:33:19 UTC","updatedISO":"2025-01-08T04:33:19+00:00","updateduk":"Jan 8, 2025 at 04:33 GMT"},"disclaimer":"This data was produced from the CoinDesk Bitcoin Price Index (USD). Non-USD currency data converted using hourly conversion rate from openexchangerates.org","chartName":"Bitcoin","bpi":{"USD":{"code":"USD","symbol":"&#36;","rate":"96,921.61","description":"United States Dollar","rate_float":96921.6095},"GBP":{"code":"GBP","symbol":"&pound;","rate":"77,302.253","description":"British Pound Sterling","rate_float":77302.2527},"EUR":{"code":"EUR","symbol":"&euro;","rate":"93,212.807","description":"Euro","rate_float":93212.8072},"CNY":{"code":"CNY","symbol":"&yen;","rate":"710,231.862","description":"Chinese Yuan","rate_float":710231.8623}}}