{"time":{"updated":"Apr 30, 2024 02:32:46 UTC","updatedISO":"2024-04-30T02:32:46+00:00","updateduk":"Apr 30, 2024 at 03:32 BST"},"disclaimer":"This data was produced from the CoinDesk Bitcoin Price Index (USD). Non-USD currency data converted using hourly conversion rate from openexchangerates.org","chartName":"Bitcoin","bpi":{"USD":{"code":"USD","symbol":"&#36;","rate":"63,689.257","description":"United States Dollar","rate_float":63689.2566},"GBP":{"code":"GBP","symbol":"&pound;","rate":"50,750.402","description":"British Pound Sterling","rate_float":50750.402},"EUR":{"code":"EUR","symbol":"&euro;","rate":"59,483.473","description":"Euro","rate_float":59483.4728},"CNY":{"code":"CNY","symbol":"&yen;","rate":"461,135.693","description":"Chinese Yuan","rate_float":461135.6934}}}