{"time":{"updated":"Jan 13, 2024 19:32:12 UTC","updatedISO":"2024-01-13T19:32:12+00:00","updateduk":"Jan 13, 2024 at 19:32 GMT"},"disclaimer":"This data was produced from the CoinDesk Bitcoin Price Index (USD). Non-USD currency data converted using hourly conversion rate from openexchangerates.org","chartName":"Bitcoin","bpi":{"USD":{"code":"USD","symbol":"&#36;","rate":"43,055.299","description":"United States Dollar","rate_float":43055.2987},"GBP":{"code":"GBP","symbol":"&pound;","rate":"33,779.465","description":"British Pound Sterling","rate_float":33779.4652},"EUR":{"code":"EUR","symbol":"&euro;","rate":"39,269.705","description":"Euro","rate_float":39269.7046},"CNY":{"code":"CNY","symbol":"&yen;","rate":"306,235.118","description":"Chinese Yuan","rate_float":306235.1177}}}