{"time":{"updated":"Dec 2, 2023 22:45:00 UTC","updatedISO":"2023-12-02T22:45:00+00:00","updateduk":"Dec 2, 2023 at 22:45 GMT"},"disclaimer":"This data was produced from the CoinDesk Bitcoin Price Index (USD). Non-USD currency data converted using hourly conversion rate from openexchangerates.org","chartName":"Bitcoin","bpi":{"USD":{"code":"USD","symbol":"&#36;","rate":"38,724.0375","description":"United States Dollar","rate_float":38724.0375},"GBP":{"code":"GBP","symbol":"&pound;","rate":"32,357.4959","description":"British Pound Sterling","rate_float":32357.4959},"EUR":{"code":"EUR","symbol":"&euro;","rate":"37,722.8662","description":"Euro","rate_float":37722.8662},"CNY":{"code":"CNY","symbol":"&yen;","rate":"40,202.5000","description":"Chinese Yuan","rate_float":40202.5}}}