{"time":{"updated":"Aug 28, 2024 11:53:15 UTC","updatedISO":"2024-08-28T11:53:15+00:00","updateduk":"Aug 28, 2024 at 12:53 BST"},"disclaimer":"This data was produced from the CoinDesk Bitcoin Price Index (USD). Non-USD currency data converted using hourly conversion rate from openexchangerates.org","chartName":"Bitcoin","bpi":{"USD":{"code":"USD","symbol":"&#36;","rate":"60,036.428","description":"United States Dollar","rate_float":60036.4284},"GBP":{"code":"GBP","symbol":"&pound;","rate":"45,420.32","description":"British Pound Sterling","rate_float":45420.3198},"EUR":{"code":"EUR","symbol":"&euro;","rate":"53,963.444","description":"Euro","rate_float":53963.4435},"CNY":{"code":"CNY","symbol":"&yen;","rate":"427,921.651","description":"Chinese Yuan","rate_float":427921.6509}}}