{"time":{"updated":"Aug 6, 2022 12:47:00 UTC","updatedISO":"2022-08-06T12:47:00+00:00","updateduk":"Aug 6, 2022 at 13:47 BST"},"disclaimer":"This data was produced from the CoinDesk Bitcoin Price Index (USD). Non-USD currency data converted using hourly conversion rate from openexchangerates.org","chartName":"Bitcoin","bpi":{"USD":{"code":"USD","symbol":"&#36;","rate":"23,180.7769","description":"United States Dollar","rate_float":23180.7769},"GBP":{"code":"GBP","symbol":"&pound;","rate":"19,369.6718","description":"British Pound Sterling","rate_float":19369.6718},"EUR":{"code":"EUR","symbol":"&euro;","rate":"22,581.4611","description":"Euro","rate_float":22581.4611},"CNY":{"code":"CNY","symbol":"&yen;","rate":"40,202.5000","description":"Chinese Yuan","rate_float":40202.5}}}