{"time":{"updated":"Aug 23, 2024 08:46:13 UTC","updatedISO":"2024-08-23T08:46:13+00:00","updateduk":"Aug 23, 2024 at 09:46 BST"},"disclaimer":"This data was produced from the CoinDesk Bitcoin Price Index (USD). Non-USD currency data converted using hourly conversion rate from openexchangerates.org","chartName":"Bitcoin","bpi":{"USD":{"code":"USD","symbol":"&#36;","rate":"61,228.552","description":"United States Dollar","rate_float":61228.5518},"GBP":{"code":"GBP","symbol":"&pound;","rate":"46,675.321","description":"British Pound Sterling","rate_float":46675.321},"EUR":{"code":"EUR","symbol":"&euro;","rate":"55,064.674","description":"Euro","rate_float":55064.6735},"CNY":{"code":"CNY","symbol":"&yen;","rate":"437,049.403","description":"Chinese Yuan","rate_float":437049.4027}}}