{"time":{"updated":"Mar 28, 2023 03:59:00 UTC","updatedISO":"2023-03-28T03:59:00+00:00","updateduk":"Mar 28, 2023 at 04:59 BST"},"disclaimer":"This data was produced from the CoinDesk Bitcoin Price Index (USD). Non-USD currency data converted using hourly conversion rate from openexchangerates.org","chartName":"Bitcoin","bpi":{"USD":{"code":"USD","symbol":"&#36;","rate":"26,974.6863","description":"United States Dollar","rate_float":26974.6863},"GBP":{"code":"GBP","symbol":"&pound;","rate":"22,539.8321","description":"British Pound Sterling","rate_float":22539.8321},"EUR":{"code":"EUR","symbol":"&euro;","rate":"26,277.2828","description":"Euro","rate_float":26277.2828},"CNY":{"code":"CNY","symbol":"&yen;","rate":"40,202.5000","description":"Chinese Yuan","rate_float":40202.5}}}