{"time":{"updated":"Oct 16, 2021 09:42:00 UTC","updatedISO":"2021-10-16T09:42:00+00:00","updateduk":"Oct 16, 2021 at 10:42 BST"},"disclaimer":"This data was produced from the CoinDesk Bitcoin Price Index (USD). Non-USD currency data converted using hourly conversion rate from openexchangerates.org","chartName":"Bitcoin","bpi":{"USD":{"code":"USD","symbol":"&#36;","rate":"61,596.1467","description":"United States Dollar","rate_float":61596.1467},"GBP":{"code":"GBP","symbol":"&pound;","rate":"44,813.4758","description":"British Pound Sterling","rate_float":44813.4758},"EUR":{"code":"EUR","symbol":"&euro;","rate":"53,101.4837","description":"Euro","rate_float":53101.4837},"CNY":{"code":"CNY","symbol":"&yen;","rate":"40,202.5000","description":"Chinese Yuan","rate_float":40202.5}}}