{"time":{"updated":"Oct 12, 2024 23:10:11 UTC","updatedISO":"2024-10-12T23:10:11+00:00","updateduk":"Oct 13, 2024 at 00:10 BST"},"disclaimer":"This data was produced from the CoinDesk Bitcoin Price Index (USD). Non-USD currency data converted using hourly conversion rate from openexchangerates.org","chartName":"Bitcoin","bpi":{"USD":{"code":"USD","symbol":"&#36;","rate":"63,305.987","description":"United States Dollar","rate_float":63305.9867},"GBP":{"code":"GBP","symbol":"&pound;","rate":"48,439.779","description":"British Pound Sterling","rate_float":48439.7785},"EUR":{"code":"EUR","symbol":"&euro;","rate":"57,850.087","description":"Euro","rate_float":57850.0868},"CNY":{"code":"CNY","symbol":"&yen;","rate":"447,332.763","description":"Chinese Yuan","rate_float":447332.7631}}}