{"time":{"updated":"Dec 2, 2021 17:44:00 UTC","updatedISO":"2021-12-02T17:44:00+00:00","updateduk":"Dec 2, 2021 at 17:44 GMT"},"disclaimer":"This data was produced from the CoinDesk Bitcoin Price Index (USD). Non-USD currency data converted using hourly conversion rate from openexchangerates.org","chartName":"Bitcoin","bpi":{"USD":{"code":"USD","symbol":"&#36;","rate":"56,572.3050","description":"United States Dollar","rate_float":56572.305},"GBP":{"code":"GBP","symbol":"&pound;","rate":"42,510.4666","description":"British Pound Sterling","rate_float":42510.4666},"EUR":{"code":"EUR","symbol":"&euro;","rate":"50,029.0956","description":"Euro","rate_float":50029.0956},"CNY":{"code":"CNY","symbol":"&yen;","rate":"40,202.5000","description":"Chinese Yuan","rate_float":40202.5}}}