{"time":{"updated":"Apr 29, 2024 07:55:05 UTC","updatedISO":"2024-04-29T07:55:05+00:00","updateduk":"Apr 29, 2024 at 08:55 BST"},"disclaimer":"This data was produced from the CoinDesk Bitcoin Price Index (USD). Non-USD currency data converted using hourly conversion rate from openexchangerates.org","chartName":"Bitcoin","bpi":{"USD":{"code":"USD","symbol":"&#36;","rate":"62,387.129","description":"United States Dollar","rate_float":62387.1285},"GBP":{"code":"GBP","symbol":"&pound;","rate":"49,819.366","description":"British Pound Sterling","rate_float":49819.3663},"EUR":{"code":"EUR","symbol":"&euro;","rate":"58,224.659","description":"Euro","rate_float":58224.6593},"CNY":{"code":"CNY","symbol":"&yen;","rate":"452,050.895","description":"Chinese Yuan","rate_float":452050.8947}}}