{"time":{"updated":"Aug 15, 2024 16:50:49 UTC","updatedISO":"2024-08-15T16:50:49+00:00","updateduk":"Aug 15, 2024 at 17:50 BST"},"disclaimer":"This data was produced from the CoinDesk Bitcoin Price Index (USD). Non-USD currency data converted using hourly conversion rate from openexchangerates.org","chartName":"Bitcoin","bpi":{"USD":{"code":"USD","symbol":"&#36;","rate":"59,545.328","description":"United States Dollar","rate_float":59545.3275},"GBP":{"code":"GBP","symbol":"&pound;","rate":"46,293.277","description":"British Pound Sterling","rate_float":46293.2767},"EUR":{"code":"EUR","symbol":"&euro;","rate":"54,202.98","description":"Euro","rate_float":54202.9802},"CNY":{"code":"CNY","symbol":"&yen;","rate":"426,189.727","description":"Chinese Yuan","rate_float":426189.7268}}}