{"time":{"updated":"Nov 24, 2024 04:16:02 UTC","updatedISO":"2024-11-24T04:16:02+00:00","updateduk":"Nov 24, 2024 at 04:16 GMT"},"disclaimer":"This data was produced from the CoinDesk Bitcoin Price Index (USD). Non-USD currency data converted using hourly conversion rate from openexchangerates.org","chartName":"Bitcoin","bpi":{"USD":{"code":"USD","symbol":"&#36;","rate":"97,700.543","description":"United States Dollar","rate_float":97700.5431},"GBP":{"code":"GBP","symbol":"&pound;","rate":"77,970.212","description":"British Pound Sterling","rate_float":77970.2115},"EUR":{"code":"EUR","symbol":"&euro;","rate":"93,780.504","description":"Euro","rate_float":93780.5042},"CNY":{"code":"CNY","symbol":"&yen;","rate":"707,645.034","description":"Chinese Yuan","rate_float":707645.0336}}}