{"time":{"updated":"Apr 19, 2024 07:50:50 UTC","updatedISO":"2024-04-19T07:50:50+00:00","updateduk":"Apr 19, 2024 at 08:50 BST"},"disclaimer":"This data was produced from the CoinDesk Bitcoin Price Index (USD). Non-USD currency data converted using hourly conversion rate from openexchangerates.org","chartName":"Bitcoin","bpi":{"USD":{"code":"USD","symbol":"&#36;","rate":"64,567.855","description":"United States Dollar","rate_float":64567.8552},"GBP":{"code":"GBP","symbol":"&pound;","rate":"51,940.772","description":"British Pound Sterling","rate_float":51940.7718},"EUR":{"code":"EUR","symbol":"&euro;","rate":"60,655.302","description":"Euro","rate_float":60655.3015},"CNY":{"code":"CNY","symbol":"&yen;","rate":"467,516.47","description":"Chinese Yuan","rate_float":467516.4695}}}