{"time":{"updated":"May 29, 2024 04:11:20 UTC","updatedISO":"2024-05-29T04:11:20+00:00","updateduk":"May 29, 2024 at 05:11 BST"},"disclaimer":"This data was produced from the CoinDesk Bitcoin Price Index (USD). Non-USD currency data converted using hourly conversion rate from openexchangerates.org","chartName":"Bitcoin","bpi":{"USD":{"code":"USD","symbol":"&#36;","rate":"68,707.646","description":"United States Dollar","rate_float":68707.6458},"GBP":{"code":"GBP","symbol":"&pound;","rate":"53,885.002","description":"British Pound Sterling","rate_float":53885.0018},"EUR":{"code":"EUR","symbol":"&euro;","rate":"63,341.579","description":"Euro","rate_float":63341.5787},"CNY":{"code":"CNY","symbol":"&yen;","rate":"488,475.29","description":"Chinese Yuan","rate_float":488475.2901}}}