{"time":{"updated":"Dec 14, 2024 04:53:58 UTC","updatedISO":"2024-12-14T04:53:58+00:00","updateduk":"Dec 14, 2024 at 04:53 GMT"},"disclaimer":"This data was produced from the CoinDesk Bitcoin Price Index (USD). Non-USD currency data converted using hourly conversion rate from openexchangerates.org","chartName":"Bitcoin","bpi":{"USD":{"code":"USD","symbol":"&#36;","rate":"101,894.959","description":"United States Dollar","rate_float":101894.9587},"GBP":{"code":"GBP","symbol":"&pound;","rate":"79,730.054","description":"British Pound Sterling","rate_float":79730.0541},"EUR":{"code":"EUR","symbol":"&euro;","rate":"96,754.358","description":"Euro","rate_float":96754.3581},"CNY":{"code":"CNY","symbol":"&yen;","rate":"738,707.882","description":"Chinese Yuan","rate_float":738707.8824}}}