{"time":{"updated":"Oct 8, 2024 04:37:38 UTC","updatedISO":"2024-10-08T04:37:38+00:00","updateduk":"Oct 8, 2024 at 05:37 BST"},"disclaimer":"This data was produced from the CoinDesk Bitcoin Price Index (USD). Non-USD currency data converted using hourly conversion rate from openexchangerates.org","chartName":"Bitcoin","bpi":{"USD":{"code":"USD","symbol":"&#36;","rate":"62,735.59","description":"United States Dollar","rate_float":62735.5903},"GBP":{"code":"GBP","symbol":"&pound;","rate":"47,916.001","description":"British Pound Sterling","rate_float":47916.0009},"EUR":{"code":"EUR","symbol":"&euro;","rate":"57,119.5","description":"Euro","rate_float":57119.5002},"CNY":{"code":"CNY","symbol":"&yen;","rate":"443,151.663","description":"Chinese Yuan","rate_float":443151.6626}}}