{"time":{"updated":"Oct 19, 2024 10:35:53 UTC","updatedISO":"2024-10-19T10:35:53+00:00","updateduk":"Oct 19, 2024 at 11:35 BST"},"disclaimer":"This data was produced from the CoinDesk Bitcoin Price Index (USD). Non-USD currency data converted using hourly conversion rate from openexchangerates.org","chartName":"Bitcoin","bpi":{"USD":{"code":"USD","symbol":"&#36;","rate":"68,307.884","description":"United States Dollar","rate_float":68307.8839},"GBP":{"code":"GBP","symbol":"&pound;","rate":"52,339.208","description":"British Pound Sterling","rate_float":52339.2083},"EUR":{"code":"EUR","symbol":"&euro;","rate":"62,826.176","description":"Euro","rate_float":62826.1762},"CNY":{"code":"CNY","symbol":"&yen;","rate":"485,108.93","description":"Chinese Yuan","rate_float":485108.9296}}}