{"time":{"updated":"May 19, 2024 17:34:47 UTC","updatedISO":"2024-05-19T17:34:47+00:00","updateduk":"May 19, 2024 at 18:34 BST"},"disclaimer":"This data was produced from the CoinDesk Bitcoin Price Index (USD). Non-USD currency data converted using hourly conversion rate from openexchangerates.org","chartName":"Bitcoin","bpi":{"USD":{"code":"USD","symbol":"&#36;","rate":"66,815.767","description":"United States Dollar","rate_float":66815.767},"GBP":{"code":"GBP","symbol":"&pound;","rate":"52,758.331","description":"British Pound Sterling","rate_float":52758.3309},"EUR":{"code":"EUR","symbol":"&euro;","rate":"61,445.45","description":"Euro","rate_float":61445.4497},"CNY":{"code":"CNY","symbol":"&yen;","rate":"473,810.648","description":"Chinese Yuan","rate_float":473810.6484}}}