{"time":{"updated":"Apr 21, 2024 11:33:53 UTC","updatedISO":"2024-04-21T11:33:53+00:00","updateduk":"Apr 21, 2024 at 12:33 BST"},"disclaimer":"This data was produced from the CoinDesk Bitcoin Price Index (USD). Non-USD currency data converted using hourly conversion rate from openexchangerates.org","chartName":"Bitcoin","bpi":{"USD":{"code":"USD","symbol":"&#36;","rate":"65,287.135","description":"United States Dollar","rate_float":65287.1347},"GBP":{"code":"GBP","symbol":"&pound;","rate":"52,782.886","description":"British Pound Sterling","rate_float":52782.8856},"EUR":{"code":"EUR","symbol":"&euro;","rate":"61,191.869","description":"Euro","rate_float":61191.8686},"CNY":{"code":"CNY","symbol":"&yen;","rate":"472,633.154","description":"Chinese Yuan","rate_float":472633.1539}}}