{"time":{"updated":"Jun 17, 2024 14:30:29 UTC","updatedISO":"2024-06-17T14:30:29+00:00","updateduk":"Jun 17, 2024 at 15:30 BST"},"disclaimer":"This data was produced from the CoinDesk Bitcoin Price Index (USD). Non-USD currency data converted using hourly conversion rate from openexchangerates.org","chartName":"Bitcoin","bpi":{"USD":{"code":"USD","symbol":"&#36;","rate":"65,498.988","description":"United States Dollar","rate_float":65498.9879},"GBP":{"code":"GBP","symbol":"&pound;","rate":"51,676.54","description":"British Pound Sterling","rate_float":51676.54},"EUR":{"code":"EUR","symbol":"&euro;","rate":"61,121.691","description":"Euro","rate_float":61121.6905},"CNY":{"code":"CNY","symbol":"&yen;","rate":"475,273.756","description":"Chinese Yuan","rate_float":475273.7558}}}