{"time":{"updated":"Dec 18, 2024 05:52:13 UTC","updatedISO":"2024-12-18T05:52:13+00:00","updateduk":"Dec 18, 2024 at 05:52 GMT"},"disclaimer":"This data was produced from the CoinDesk Bitcoin Price Index (USD). Non-USD currency data converted using hourly conversion rate from openexchangerates.org","chartName":"Bitcoin","bpi":{"USD":{"code":"USD","symbol":"&#36;","rate":"103,858.311","description":"United States Dollar","rate_float":103858.3109},"GBP":{"code":"GBP","symbol":"&pound;","rate":"81,266.324","description":"British Pound Sterling","rate_float":81266.3241},"EUR":{"code":"EUR","symbol":"&euro;","rate":"98,618.659","description":"Euro","rate_float":98618.6591},"CNY":{"code":"CNY","symbol":"&yen;","rate":"752,941.597","description":"Chinese Yuan","rate_float":752941.5966}}}