{"time":{"updated":"Apr 10, 2024 09:09:28 UTC","updatedISO":"2024-04-10T09:09:28+00:00","updateduk":"Apr 10, 2024 at 10:09 BST"},"disclaimer":"This data was produced from the CoinDesk Bitcoin Price Index (USD). Non-USD currency data converted using hourly conversion rate from openexchangerates.org","chartName":"Bitcoin","bpi":{"USD":{"code":"USD","symbol":"&#36;","rate":"69,003.123","description":"United States Dollar","rate_float":69003.1233},"GBP":{"code":"GBP","symbol":"&pound;","rate":"54,381.362","description":"British Pound Sterling","rate_float":54381.3615},"EUR":{"code":"EUR","symbol":"&euro;","rate":"63,565.47","description":"Euro","rate_float":63565.4702},"CNY":{"code":"CNY","symbol":"&yen;","rate":"499,071.99","description":"Chinese Yuan","rate_float":499071.9896}}}