{"time":{"updated":"May 7, 2024 04:44:45 UTC","updatedISO":"2024-05-07T04:44:45+00:00","updateduk":"May 7, 2024 at 05:44 BST"},"disclaimer":"This data was produced from the CoinDesk Bitcoin Price Index (USD). Non-USD currency data converted using hourly conversion rate from openexchangerates.org","chartName":"Bitcoin","bpi":{"USD":{"code":"USD","symbol":"&#36;","rate":"63,442.11","description":"United States Dollar","rate_float":63442.11},"GBP":{"code":"GBP","symbol":"&pound;","rate":"50,522.315","description":"British Pound Sterling","rate_float":50522.3146},"EUR":{"code":"EUR","symbol":"&euro;","rate":"58,915.008","description":"Euro","rate_float":58915.0079},"CNY":{"code":"CNY","symbol":"&yen;","rate":"450,451.669","description":"Chinese Yuan","rate_float":450451.6694}}}