{"time":{"updated":"Nov 23, 2024 13:59:19 UTC","updatedISO":"2024-11-23T13:59:19+00:00","updateduk":"Nov 23, 2024 at 13:59 GMT"},"disclaimer":"This data was produced from the CoinDesk Bitcoin Price Index (USD). Non-USD currency data converted using hourly conversion rate from openexchangerates.org","chartName":"Bitcoin","bpi":{"USD":{"code":"USD","symbol":"&#36;","rate":"98,245.919","description":"United States Dollar","rate_float":98245.9191},"GBP":{"code":"GBP","symbol":"&pound;","rate":"78,408.594","description":"British Pound Sterling","rate_float":78408.5944},"EUR":{"code":"EUR","symbol":"&euro;","rate":"94,303.998","description":"Euro","rate_float":94303.9981},"CNY":{"code":"CNY","symbol":"&yen;","rate":"711,595.192","description":"Chinese Yuan","rate_float":711595.1921}}}